clustimage/__init__.py
clustimage/clustimage.py
clustimage/examples.py
clustimage/exif.py
clustimage-1.7.1.dist-info/licenses/LICENSE
clustimage-1.7.1.dist-info/METADATA
clustimage-1.7.1.dist-info/WHEEL
clustimage-1.7.1.dist-info/top_level.txt
clustimage-1.7.1.dist-info/RECORD
