Metadata-Version: 2.4
Name: clustimage
Version: 1.7.1
Summary: Python package clustimage is for unsupervised clustering of images.
Author-email: Erdogan Taskesen <erdogant@gmail.com>
License-Expression: MIT
Project-URL: Homepage, https://erdogant.github.io/clustimage
Project-URL: Download, https://github.com/erdogant/clustimage/archive/{version}.tar.gz
Keywords: clustering,images,unsupervised learning
Classifier: Programming Language :: Python :: 3
Classifier: Operating System :: OS Independent
Classifier: Intended Audience :: Education
Classifier: Intended Audience :: Science/Research
Classifier: Operating System :: Unix
Classifier: Operating System :: Microsoft :: Windows
Classifier: Operating System :: MacOS
Classifier: Topic :: Scientific/Engineering :: Artificial Intelligence
Requires-Python: <3.14,>=3.8
License-File: LICENSE
Requires-Dist: datazets>=1.0.0
Requires-Dist: scatterd>=1.3.6
Requires-Dist: ismember
Requires-Dist: pypickle
Requires-Dist: pca>=2.0.4
Requires-Dist: distfit
Requires-Dist: clusteval>=2.1.5
Requires-Dist: colourmap>=1.1.16
Requires-Dist: numpy
Requires-Dist: pandas
Requires-Dist: tqdm
Requires-Dist: scikit-learn
Requires-Dist: scikit-image
Requires-Dist: matplotlib
Requires-Dist: scipy
Requires-Dist: piexif
Requires-Dist: imagehash
Requires-Dist: pillow-heif
Requires-Dist: geopy
Requires-Dist: folium
Requires-Dist: opencv-python-headless
Dynamic: license-file
